promptlog/__init__.py
promptlog/manager.py
promptlog-0.1.0.dist-info/LICENSE
promptlog-0.1.0.dist-info/METADATA
promptlog-0.1.0.dist-info/WHEEL
promptlog-0.1.0.dist-info/top_level.txt
promptlog-0.1.0.dist-info/RECORD
