Metadata-Version: 2.1
Name: promptlog
Version: 0.1.0
Summary: A version control tool for prompts
Home-page: https://github.com/hscspring/promptlog
Author: Yam
Author-email: Yam <haoshaochun@gmail.com>
License: MIT License
Project-URL: Homepage, https://github.com/hscspring/promptlog
Classifier: Development Status :: 3 - Alpha
Classifier: Intended Audience :: Developers
Classifier: License :: OSI Approved :: MIT License
Classifier: Programming Language :: Python :: 3
Classifier: Programming Language :: Python :: 3.7
Classifier: Programming Language :: Python :: 3.8
Classifier: Programming Language :: Python :: 3.9
Classifier: Programming Language :: Python :: 3.10
Requires-Python: >=3.7
License-File: LICENSE
Requires-Dist: deepdiff>=5.8.1
Requires-Dist: appdirs>=1.4.4
